MANIFEST.in
README.md
setup.py
src/dt_duckiematrix_messages/CBorMessage.py
src/dt_duckiematrix_messages/CameraFrame.py
src/dt_duckiematrix_messages/EmptyMessage.py
src/dt_duckiematrix_messages/LEDsCommand.py
src/dt_duckiematrix_messages/LayerMessage.py
src/dt_duckiematrix_messages/NetworkEndpoint.py
src/dt_duckiematrix_messages/NetworkJoin.py
src/dt_duckiematrix_messages/NetworkJoined.py
src/dt_duckiematrix_messages/NetworkLeave.py
src/dt_duckiematrix_messages/NetworkReady.py
src/dt_duckiematrix_messages/StringMessage.py
src/dt_duckiematrix_messages/TimeOfFlightRange.py
src/dt_duckiematrix_messages/WheelEncoderTicks.py
src/dt_duckiematrix_messages/WheelsCommand.py
src/dt_duckiematrix_messages/__init__.py
src/dt_duckiematrix_protocols/__init__.py
src/dt_duckiematrix_protocols/matrix.py
src/dt_duckiematrix_protocols/commons/CBORProtocol.py
src/dt_duckiematrix_protocols/commons/LayerProtocol.py
src/dt_duckiematrix_protocols/commons/ProtocolAbs.py
src/dt_duckiematrix_protocols/commons/__init__.py
src/dt_duckiematrix_protocols/commons/socket.py
src/dt_duckiematrix_protocols/robot/RobotProtocols.py
src/dt_duckiematrix_protocols/robot/RobotsManager.py
src/dt_duckiematrix_protocols/robot/__init__.py
src/dt_duckiematrix_protocols/robot/robots.py
src/dt_duckiematrix_protocols/robot/features/__init__.py
src/dt_duckiematrix_protocols/robot/features/lights.py
src/dt_duckiematrix_protocols/robot/features/motion.py
src/dt_duckiematrix_protocols/robot/features/sensors.py
src/dt_duckiematrix_protocols/types/__init__.py
src/dt_duckiematrix_protocols/types/colors.py
src/dt_duckiematrix_protocols/types/geometry.py
src/dt_duckiematrix_protocols/types/markers.py
src/dt_duckiematrix_protocols/utils/Color.py
src/dt_duckiematrix_protocols/utils/MonitoredCondition.py
src/dt_duckiematrix_protocols/utils/MonitoredObject.py
src/dt_duckiematrix_protocols/utils/Pose3D.py
src/dt_duckiematrix_protocols/utils/Vector3.py
src/dt_duckiematrix_protocols/utils/__init__.py
src/dt_duckiematrix_protocols_ente.egg-info/PKG-INFO
src/dt_duckiematrix_protocols_ente.egg-info/SOURCES.txt
src/dt_duckiematrix_protocols_ente.egg-info/dependency_links.txt
src/dt_duckiematrix_protocols_ente.egg-info/top_level.txt
