Metadata-Version: 2.1
Name: dt-duckiematrix-protocols-ente
Version: 0.1.8
Summary: UNKNOWN
Home-page: http://github.com/duckietown/lib-dt-duckiematrix-protocols
Author: Andrea F. Daniele
Author-email: afdaniele@duckietown.com
License: UNKNOWN
Platform: UNKNOWN
